package_jwalika/__init__.py
package_jwalika/api_dealer.py
package_jwalika-0.1.dist-info/METADATA
package_jwalika-0.1.dist-info/WHEEL
package_jwalika-0.1.dist-info/top_level.txt
package_jwalika-0.1.dist-info/RECORD
